main/__init__.py
main/controller.py
main/install.py
main/main_loop.py
main/view.py
main/views/__init__.py
main/views/default_view.py
main/views/load_view.py
main/views/network_status_view.py
main/views/reboot_view.py
main/views/shutdown_view.py
main/views/test_view.py
raspi_view-0.5.0.data/scripts/raspi-view
tests/__init__.py
tests/test.py
raspi_view-0.5.0.dist-info/LICENSE
raspi_view-0.5.0.dist-info/METADATA
raspi_view-0.5.0.dist-info/WHEEL
raspi_view-0.5.0.dist-info/top_level.txt
raspi_view-0.5.0.dist-info/RECORD
