Metadata-Version: 2.1
Name: raspi-view
Version: 0.5.0
Summary: An app to display different views on a Raspberry Pi HAT with display sh1106
Home-page: https://github.com/zsfarkas/raspi-view
Author: Zsolt Farkas
License: UNKNOWN
Keywords: raspi,raspberry,hat,display,view,monitor,screen
Platform: UNKNOWN
Classifier: Programming Language :: Python :: 3
Classifier: License :: OSI Approved :: MIT License
Classifier: Operating System :: OS Independent
